tests/PublishHistoryTest.py
tests/__init__.py
tests/dp_is_login_test.py
tests/test001.py
tests/test_example.py
tests/test_wechat_draft.py
tests/wechat_draft_test.py
wechat_draft/__init__.py
wechat_draft/wechat_draft.py
wechat_draft/utils/__init__.py
wechat_draft/utils/check_dp_login.py
wechat_draft/utils/constants.py
wechat_draft/utils/error_code.py
wechat_draft/utils/get_publish_history.py
wechat_draft/utils/logger.py
wechat_draft-0.1.16.dist-info/licenses/LICENSE
wechat_draft-0.1.16.dist-info/METADATA
wechat_draft-0.1.16.dist-info/WHEEL
wechat_draft-0.1.16.dist-info/top_level.txt
wechat_draft-0.1.16.dist-info/RECORD
