Metadata-Version: 2.4
Name: wechat_draft
Version: 0.1.16
Summary: 新建微信公众号文章草稿
Home-page: https://gitee.com/xiaoqiangclub/wechat_draft
Author: XiaoqiangClub
Author-email: xiaoqiangclub@hotmail.com
License: MIT
Classifier: Programming Language :: Python :: 3
Classifier: License :: OSI Approved :: MIT License
Classifier: Operating System :: OS Independent
Requires-Python: >=3.8
License-File: LICENSE
Requires-Dist: requests
Requires-Dist: pillow
Provides-Extra: windows
Requires-Dist: DrissionPage; extra == "windows"
Requires-Dist: pypiwin32; extra == "windows"
Provides-Extra: linux
Dynamic: author
Dynamic: author-email
Dynamic: classifier
Dynamic: description
Dynamic: description-content-type
Dynamic: home-page
Dynamic: license
Dynamic: license-file
Dynamic: provides-extra
Dynamic: requires-dist
Dynamic: requires-python
Dynamic: summary
